contextuallogging/__init__.py
contextuallogging/_context.py
contextuallogging/_context_management.py
contextuallogging/_contextual_formatter.py
contextuallogging/py.typed
contextuallogging-1.0.3.dist-info/LICENSE
contextuallogging-1.0.3.dist-info/METADATA
contextuallogging-1.0.3.dist-info/WHEEL
contextuallogging-1.0.3.dist-info/top_level.txt
contextuallogging-1.0.3.dist-info/RECORD
