Metadata-Version: 2.1
Name: contextuallogging
Version: 1.0.3
Summary: Pure-Python semantic logging library with context-local values.
Author-email: Charles Andrews <cfandrews@outlook.com>
License: MIT License
Project-URL: Homepage, https://github.com/cfandrews/PythonContextualLogging
Requires-Python: >=3.8
License-File: LICENSE
Provides-Extra: build
Requires-Dist: pre-commit ==3.5.0 ; extra == 'build'
Requires-Dist: isort ==5.12.0 ; extra == 'build'
Requires-Dist: ruff ==0.1.6 ; extra == 'build'
Requires-Dist: mypy ==1.7.1 ; extra == 'build'
Requires-Dist: pytest ==7.4.3 ; extra == 'build'
Requires-Dist: assertpy ==1.1 ; extra == 'build'
Requires-Dist: pytest-cov ==4.1.0 ; extra == 'build'
Requires-Dist: build ==1.0.3 ; extra == 'build'
Requires-Dist: pdoc ==14.1.0 ; extra == 'build'
